<?xml version="1.0" encoding="utf-8"?>
<provider>
  <id major-version="1.0" version="1">ab-money-2tbank</id>
  <name>2ТБанк</name>
  <description>
    2ТБанк - состояние счетов
  </description>
  <author>Victor Vostrikov &lt;v.vostrikov@softworks.ru&gt;</author>
  <files>
    <icon>icon.png</icon> <!-- файл иконки -->
    <preferences>preferences.xml</preferences> <!-- Файл настроек -->
    <js>main.js</js> <!-- необходим как минимум один файл с функцией main() -->
    <js>library.js</js> <!-- необходим как минимум один файл с функцией main() -->
    <js>api:jquery.min.js</js>
    <history>history.xml</history> <!-- История изменений версий провайдера -->   
  </files>
  <counters>
    <counter id="t_sum" name="Сумма на счету" type="numeric"/>
    <counter id="t_percent" name="Процент" type="numeric"/>
    <counter id="t_percent_sum" name="Сумма процентов" type="numeric"/>
    <counter id="t_percent_date" name="Дата начисления" type="time" format="dd.MM.yyyy"/>
  </counters>
  <keywords>
   2ТБанк, 2TBank, Банк-Т, банк 
  </keywords>  
  <type>
     money
  </type>
  <country>
     ru
  </country>
</provider>