<?xml version="1.0" encoding="utf-8"?>
<provider>
	<id version="2">ab-internet-ellcom</id>
	<api flags="no_browser"/>
	<name>Ellco (Электросвязь)</name>
	<description html="true"><![CDATA[
	<p>Предоставляет информацию о балансе провайдера Ellco (Электросвязь) http://www.ellco.ru/</p>
	<p>Информация берется из личного кабинета https://bill.ellcom.ru/bgbilling/webexecuter</p>
	]]></description>
	<author>Stark &lt;support@starksoft.ru&gt;</author>
	<files>
		<icon>icon.png</icon>
		<preferences>preferences.xml</preferences>
		<js>library.js</js>
		<js>main.js</js>
		<history>history.xml</history>
	</files>
	<counters>
		<counter id="balance" name="Баланс" units=" р"/>
	</counters>
	<keywords></keywords>
	<type>internet</type>
	<country>ru</country>
</provider>