<?xml version="1.0" encoding="utf-8"?>
<provider>
	<id version="1">ab-internet-net-city</id>
	<api flags="no_browser"/>
	<name>Net-City (Украина)</name>
	<description html="true"><![CDATA[
	<p>Предоставляет информацию о балансе провайдера Net-City</p>
	<p>Информация берется из личного кабинета https://stat.net-city.net/index.php</p>
	]]></description>
	<author>Stark &lt;support@starksoft.ru&gt;</author>
	<files>
		<icon>icon.png</icon>
		<preferences>preferences.xml</preferences>
		<js>library.js</js>
		<js>main.js</js>
		<history>history.xml</history>
	</files>
	<counters>
		<counter id="balance" name="Баланс" units=" грн"/>
		<counter id="fio" name="ФИО" type="text"/>
		<counter id="days" name="Дней до отключения" units=" дн"/>
	</counters>
	<keywords></keywords>
	<type>internet</type>
	<country>ua</country>
</provider>