<?xml version="1.0" encoding="utf-8"?>
<provider>
	<id version="1">ab-internet-norcom</id>
	<api flags="no_browser"/>
	<name>НорКом (Норильск)</name>
	<description html="true"><![CDATA[
	<p>Предоставляет информацию о балансе интернет провайдера НорКом г. Норильск.</p>
	<p>Информация берется из личного кабинета http://www.norcom.ru/bill/msn/main.htms</p>
	]]></description>
	<author>Stark &lt;support@starksoft.ru&gt;</author>
	<files>
		<icon>icon.png</icon>
		<preferences>preferences.xml</preferences>
		<js>library.js</js>
		<js>main.js</js>
		<history>history.xml</history>
	</files>
	<counters>
		<counter id="balance" name="Баланс" units=" р"/>
		<counter id="accnum" name="Лицевой счёт" type="text"/>
	</counters>
	<keywords></keywords>
	<type>internet</type>
	<country>ru</country>
</provider>